LICENSE
MANIFEST.in
README.md
setup.py
dirtytext/__init__.py
dirtytext/__main__.py
dirtytext/results.py
dirtytext/unicode_db.py
dirtytext/unitools.py
dirtytext.egg-info/PKG-INFO
dirtytext.egg-info/SOURCES.txt
dirtytext.egg-info/dependency_links.txt
dirtytext.egg-info/entry_points.txt
dirtytext.egg-info/top_level.txt
dirtytext/data/categories.json
dirtytext/data/confusables.json