Metadata-Version: 2.1
Name: dirtytext
Version: 1.0.0
Summary: Searches for [ab]using of Unicode glyphs
Home-page: https://github.com/jacopodl/dirtytext
Author: Jacopo De Luca
Author-email: jacopo.delu@gmail.com
License: GNU General Public License v3
Keywords: dirty,text,tool,unicode,UTF-8,glyph
Platform: UNKNOWN
Classifier: Development Status :: 5 - Production/Stable
Classifier: Intended Audience :: Developers
Classifier: License :: OSI Approved :: GNU General Public License v3 (GPLv3)
Classifier: Programming Language :: Python :: 3
